odoo/addons/agreement_account/README.rst
odoo/addons/agreement_account/__init__.py
odoo/addons/agreement_account/__manifest__.py
odoo/addons/agreement_account/i18n/agreement_account.pot
odoo/addons/agreement_account/i18n/es.po
odoo/addons/agreement_account/i18n/es_AR.po
odoo/addons/agreement_account/i18n/it.po
odoo/addons/agreement_account/i18n/sv.po
odoo/addons/agreement_account/models/__init__.py
odoo/addons/agreement_account/models/account_move.py
odoo/addons/agreement_account/models/agreement.py
odoo/addons/agreement_account/readme/CONTRIBUTORS.md
odoo/addons/agreement_account/readme/DESCRIPTION.md
odoo/addons/agreement_account/security/ir.model.access.csv
odoo/addons/agreement_account/static/description/icon.png
odoo/addons/agreement_account/static/description/index.html
odoo/addons/agreement_account/tests/__init__.py
odoo/addons/agreement_account/tests/test_agreement.py
odoo/addons/agreement_account/views/account_move.xml
odoo/addons/agreement_account/views/agreement.xml
odoo_addon_agreement_account-18.0.1.0.2.1.dist-info/METADATA
odoo_addon_agreement_account-18.0.1.0.2.1.dist-info/WHEEL
odoo_addon_agreement_account-18.0.1.0.2.1.dist-info/top_level.txt
odoo_addon_agreement_account-18.0.1.0.2.1.dist-info/RECORD
