Metadata-Version: 2.1
Name: odoo-addon-agreement_account
Version: 18.0.1.0.2.1
Requires-Python: >=3.10
Requires-Dist: odoo-addon-agreement==18.0.*
Requires-Dist: odoo==18.0.*
Summary: Agreement on invoices
Home-page: https://github.com/OCA/agreement
License: AGPL-3
Author: Akretion, Odoo Community Association (OCA)
Author-email: support@odoo-community.org
Classifier: Programming Language :: Python
Classifier: Framework :: Odoo
Classifier: Framework :: Odoo :: 18.0
Classifier: License :: OSI Approved :: GNU Affero General Public License v3
Classifier: Development Status :: 4 - Beta
